dsrw/__init__.py
dsrw/app.py
dsrw/constants.py
dsrw/helper.py
dsrw/request.py
dsrw/response.py
dsrw/router.py
dsrw-0.1.4.dist-info/DESCRIPTION.rst
dsrw-0.1.4.dist-info/METADATA
dsrw-0.1.4.dist-info/RECORD
dsrw-0.1.4.dist-info/WHEEL
dsrw-0.1.4.dist-info/metadata.json
dsrw-0.1.4.dist-info/top_level.txt
