Metadata-Version: 2.0
Name: dsrw
Version: 0.1.4
Summary: Dead simple restful wsgi applications
Home-page: https://github.com/regiontog/dsrw
Author: Erlend Tobiassen
Author-email: erlentob@stud.ntnu.no
License: MIT
Keywords: wsgi development restful
Platform: UNKNOWN
Classifier: Development Status :: 3 - Alpha
Classifier: Intended Audience :: Developers
Classifier: License :: OSI Approved :: MIT License
Classifier: Programming Language :: Python :: 3.6
Requires-Dist: querystring-parser
Requires-Dist: six
Requires-Dist: ujson
